eskmo/__init__.cp312-win_amd64.pyd
eskmo/__init__.pyi
eskmo/request.cp312-win_amd64.pyd
eskmo/request.pyi
eskmo/requirements.txt
eskmo/trading.cp312-win_amd64.pyd
eskmo/trading.pyi
eskmo/base/__init__.cp312-win_amd64.pyd
eskmo/base/__init__.pyi
eskmo/base/client.cp312-win_amd64.pyd
eskmo/base/client.pyi
eskmo/base/connection.cp312-win_amd64.pyd
eskmo/base/connection.pyi
eskmo/base/extension.cp312-win_amd64.pyd
eskmo/base/extension.pyi
eskmo/base/function.cp312-win_amd64.pyd
eskmo/base/function.pyi
eskmo/base/handler.cp312-win_amd64.pyd
eskmo/base/handler.pyi
eskmo/base/interface.cp312-win_amd64.pyd
eskmo/base/interface.pyi
eskmo/base/mvqueue.cp312-win_amd64.pyd
eskmo/base/mvqueue.pyi
eskmo/base/mvtype.cp312-win_amd64.pyd
eskmo/base/mvtype.pyi
eskmo/base/runner.cp312-win_amd64.pyd
eskmo/base/runner.pyi
eskmo/base/store.cp312-win_amd64.pyd
eskmo/base/store.pyi
eskmo/base/subscribable.cp312-win_amd64.pyd
eskmo/base/subscribable.pyi
eskmo/base/types.cp312-win_amd64.pyd
eskmo/base/types.pyi
eskmo/cli/__init__.cp312-win_amd64.pyd
eskmo/cli/__init__.pyi
eskmo/cli/climain.cp312-win_amd64.pyd
eskmo/cli/climain.pyi
eskmo/cli/install.cp312-win_amd64.pyd
eskmo/cli/install.pyi
eskmo/cli/system.cp312-win_amd64.pyd
eskmo/cli/system.pyi
eskmo/client/console.cp312-win_amd64.pyd
eskmo/client/console.pyi
eskmo/client/localgrpc.cp312-win_amd64.pyd
eskmo/client/localgrpc.pyi
eskmo/client/localsocketio.cp312-win_amd64.pyd
eskmo/client/localsocketio.pyi
eskmo/client/localzmq.cp312-win_amd64.pyd
eskmo/client/localzmq.pyi
eskmo/config/release.cp312-win_amd64.pyd
eskmo/config/release.pyi
eskmo/config/skcom.cp312-win_amd64.pyd
eskmo/config/skcom.pyi
eskmo/connection/base.cp312-win_amd64.pyd
eskmo/connection/base.pyi
eskmo/connection/best5.cp312-win_amd64.pyd
eskmo/connection/best5.pyi
eskmo/connection/event.cp312-win_amd64.pyd
eskmo/connection/event.pyi
eskmo/connection/kline.cp312-win_amd64.pyd
eskmo/connection/kline.pyi
eskmo/connection/quote.cp312-win_amd64.pyd
eskmo/connection/quote.pyi
eskmo-0.0.6.dist-info/METADATA
eskmo-0.0.6.dist-info/WHEEL
eskmo-0.0.6.dist-info/entry_points.txt
eskmo-0.0.6.dist-info/top_level.txt
eskmo-0.0.6.dist-info/RECORD
