Metadata-Version: 2.4
Name: eskmo
Version: 0.0.6
Summary: eskmo
Home-page: https://github.com/ProjectEskmo/eskmo
Author: eskmo
Author-email: fatfingererr@gmail.com
Platform: Windows
Classifier: Development Status :: 1 - Planning
Classifier: Natural Language :: English
Classifier: Natural Language :: Chinese (Traditional)
Classifier: Environment :: Console
Classifier: Intended Audience :: Developers
Classifier: Programming Language :: Python :: 3
Classifier: Programming Language :: Python :: 3 :: Only
Classifier: Programming Language :: Python :: 3.9
Classifier: Programming Language :: Python :: 3.10
Classifier: Programming Language :: Python :: 3.11
Classifier: Programming Language :: Python :: 3.12
Classifier: Programming Language :: Python :: 3.13
Classifier: Topic :: Office/Business :: Financial :: Investment
Classifier: Topic :: Software Development :: Libraries :: Python Modules
Classifier: Operating System :: Microsoft :: Windows
Requires-Python: >=3.9
Requires-Dist: chardet>=5.2.0
Requires-Dist: colorama>=0.4.6
Requires-Dist: comtypes>=1.1.10
Requires-Dist: psutil>=5.9.5
Requires-Dist: python-dotenv>=1.0.0
Requires-Dist: pywin32>=300
Requires-Dist: pyzmq>=22.0.3
Requires-Dist: click>=8.1.7
Requires-Dist: setuptools>=79.0.0
Dynamic: author
Dynamic: author-email
Dynamic: classifier
Dynamic: description
Dynamic: description-content-type
Dynamic: home-page
Dynamic: platform
Dynamic: requires-dist
Dynamic: requires-python
Dynamic: summary
